ziyo_lang/__init__.py
ziyo_lang/cli.py
ziyo_lang/compiler.py
ziyo_lang/examples/array.zs
ziyo_lang/examples/demo.zs
ziyo_lang/examples/hisob.zs
ziyo_lang/examples/murakkab.zs
ziyo_lang/examples/oddiiy.zs
ziyo_lang/examples/salom.zs
ziyo_lang-1.0.1.dist-info/licenses/LICENSE
ziyo_lang-1.0.1.dist-info/METADATA
ziyo_lang-1.0.1.dist-info/WHEEL
ziyo_lang-1.0.1.dist-info/entry_points.txt
ziyo_lang-1.0.1.dist-info/top_level.txt
ziyo_lang-1.0.1.dist-info/RECORD
