Metadata-Version: 2.4
Name: ziyo-lang
Version: 1.0.1
Summary: Ziyo - O'zbekcha dasturlash tili
Home-page: https://t.me/UzMaxBoy
Author: Yoqubov Javohir
Author-email: RAKUZEN UZ <RaKUZENUZ@gmail.com>
License: MIT
Project-URL: Homepage, https://t.me/UzMaxBoy
Project-URL: Repository, https://t.me/UzMaxBoy
Project-URL: Documentation, https://t.me/UzMaxBoy
Keywords: uzbek,programming-language,transpiler,ziyo
Classifier: Development Status :: 4 - Beta
Classifier: Intended Audience :: Developers
Classifier: License :: OSI Approved :: MIT License
Classifier: Programming Language :: Python :: 3
Classifier: Programming Language :: Python :: 3.8
Classifier: Programming Language :: Python :: 3.9
Classifier: Programming Language :: Python :: 3.10
Classifier: Programming Language :: Python :: 3.11
Classifier: Programming Language :: Python :: 3.12
Classifier: Topic :: Software Development :: Interpreters
Classifier: Topic :: Software Development :: Libraries :: Python Modules
Requires-Python: >=3.8
License-File: LICENSE
Dynamic: author
Dynamic: home-page
Dynamic: license-file
Dynamic: requires-python
